LICENSE.TXT
README.md
setup.py
selfcord/__init__.py
selfcord/account.py
selfcord/channel2.py
selfcord/embed.py
selfcord/guild2.py
selfcord/message2.py
selfcord/messages.py
selfcord/selfcord.py
selfcord/user2.py
selfcord/userinfo.py
selfcord/utils.py
selfcord/wrapper.py
selfcord.egg-info/PKG-INFO
selfcord.egg-info/SOURCES.txt
selfcord.egg-info/dependency_links.txt
selfcord.egg-info/requires.txt
selfcord.egg-info/top_level.txt